illallangi/data/residential/__init__.py
illallangi/data/residential/__version__.py
illallangi/data/residential/apps.py
illallangi/data/residential/adapters/__init__.py
illallangi/data/residential/adapters/residential.py
illallangi/data/residential/admin/__init__.py
illallangi/data/residential/admin/residence.py
illallangi/data/residential/checks/__init__.py
illallangi/data/residential/checks/rdf.py
illallangi/data/residential/checks/residential.py
illallangi/data/residential/diffsyncmodels/__init__.py
illallangi/data/residential/diffsyncmodels/residence.py
illallangi/data/residential/migrations/0001_initial.py
illallangi/data/residential/migrations/__init__.py
illallangi/data/residential/models/__init__.py
illallangi/data/residential/models/residence.py
illallangi/data/residential/static/residential/residences.jpg
illallangi/data/residential/templates/residential/residence_detail.html
illallangi/data/residential/templates/residential/residence_list.html
illallangi/data/residential/views/__init__.py
illallangi/data/residential/views/residence_detail.py
illallangi/data/residential/views/residence_list.py
illallangi_data_residential-0.3.0.dist-info/METADATA
illallangi_data_residential-0.3.0.dist-info/WHEEL
illallangi_data_residential-0.3.0.dist-info/entry_points.txt
illallangi_data_residential-0.3.0.dist-info/licenses/LICENSE
illallangi_data_residential-0.3.0.dist-info/RECORD
